README
setup.py
bambu_webhooks/__init__.py
bambu_webhooks/cron.py
bambu_webhooks/forms.py
bambu_webhooks/helpers.py
bambu_webhooks/menus.py
bambu_webhooks/models.py
bambu_webhooks/sites.py
bambu_webhooks/urls.py
bambu_webhooks/views.py
bambu_webhooks.egg-info/PKG-INFO
bambu_webhooks.egg-info/SOURCES.txt
bambu_webhooks.egg-info/dependency_links.txt
bambu_webhooks.egg-info/requires.txt
bambu_webhooks.egg-info/top_level.txt
bambu_webhooks/migrations/0001_initial.py
bambu_webhooks/migrations/__init__.py
bambu_webhooks/templates/webhooks/base.html
bambu_webhooks/templates/webhooks/manage.html