Metadata-Version: 1.1
Name: bambu-webhooks
Version: 2.0
Summary: Create webhooks and allow users to assign URLs to them
Home-page: https://github.com/iamsteadman/bambu-webhooks
Author: Steadman
Author-email: mark@steadman.io
License: UNKNOWN
Platform: UNKNOWN
Classifier: Development Status :: 4 - Beta
Classifier: Environment :: Web Environment
Classifier: Framework :: Django
